deeptracy_core/__init__.py
deeptracy_core/config.py
deeptracy_core/decorator.py
deeptracy_core/docker_helpers.py
deeptracy_core/utils.py
deeptracy_core/dal/__init__.py
deeptracy_core/dal/database.py
deeptracy_core/dal/models.py
deeptracy_core/dal/plugin_results.py
deeptracy_core/dal/plugin/__init__.py
deeptracy_core/dal/plugin/manager.py
deeptracy_core/dal/plugin/model.py
deeptracy_core/dal/project/__init__.py
deeptracy_core/dal/project/manager.py
deeptracy_core/dal/project/model.py
deeptracy_core/dal/project/project_hooks.py
deeptracy_core/dal/project/repo_auth.py
deeptracy_core/dal/scan/__init__.py
deeptracy_core/dal/scan/manager.py
deeptracy_core/dal/scan/model.py
deeptracy_core/dal/scan_analysis/__init__.py
deeptracy_core/dal/scan_analysis/manager.py
deeptracy_core/dal/scan_analysis/model.py
deeptracy_core/dal/scan_dep/__init__.py
deeptracy_core/dal/scan_dep/manager.py
deeptracy_core/dal/scan_dep/model.py
deeptracy_core_dev-0.0.27.dist-info/DESCRIPTION.rst
deeptracy_core_dev-0.0.27.dist-info/METADATA
deeptracy_core_dev-0.0.27.dist-info/RECORD
deeptracy_core_dev-0.0.27.dist-info/WHEEL
deeptracy_core_dev-0.0.27.dist-info/metadata.json
deeptracy_core_dev-0.0.27.dist-info/top_level.txt
tests/__init__.py
tests/unit/__init__.py
tests/unit/base_test.py
tests/unit/mock_db.py
tests/unit/test_docker_helpers.py
tests/unit/dal/__init__.py
tests/unit/dal/test_database.py
tests/unit/dal/test_plugin_manager.py
tests/unit/dal/test_plugin_results.py
tests/unit/dal/test_project_manager.py
tests/unit/dal/test_scan_analysis_manager.py
tests/unit/dal/test_scan_dep_manager.py
tests/unit/dal/test_scan_manager.py
